dishook/__init__.py
dishook_py-1.1.dist-info/METADATA
dishook_py-1.1.dist-info/WHEEL
dishook_py-1.1.dist-info/top_level.txt
dishook_py-1.1.dist-info/RECORD
