Metadata-Version: 2.1
Name: dishook-py
Version: 1.1
Summary: discord webhook client.
Home-page: https://github.com/sonyakun/dishook
Author: sonyakun
Author-email: sonyaumg@gmail.com
Maintainer: sonyakun
Maintainer-email: sonyaumg@gmail.com
License: MIT
Platform: UNKNOWN
Classifier: Intended Audience :: Science/Research
Classifier: License :: OSI Approved :: BSD License
Classifier: Programming Language :: Python :: 3
Classifier: Programming Language :: Python :: 3.6
Classifier: Programming Language :: Python :: 3.7
Classifier: Programming Language :: Python :: 3.8
Classifier: Programming Language :: Python :: 3.9
Classifier: Programming Language :: Python :: 3 :: Only
Classifier: Topic :: Scientific/Engineering
Classifier: Topic :: Scientific/Engineering :: Visualization
Classifier: Topic :: Scientific/Engineering :: Artificial Intelligence
Classifier: Topic :: Multimedia :: Graphics
Classifier: Framework :: Matplotlib
Requires-Python: >=3.6
Requires-Dist: asyncio
Requires-Dist: requests
Requires-Dist: aiohttp
Provides-Extra: tutorial
Requires-Dist: mlxtend (>=0.18.0) ; extra == 'tutorial'
Requires-Dist: xgboost (>=1.4.2) ; extra == 'tutorial'
